{
 "actions": [],
 "allow_rename": 1,
 "creation": "2023-12-02 14:24:02.699035",
 "doctype": "DocType",
 "editable_grid": 1,
 "engine": "InnoDB",
 "field_order": [
  "old_blanket_order"
 ],
 "fields": [
  {
   "fieldname": "old_blanket_order",
   "fieldtype": "Link",
   "in_list_view": 1,
   "label": "Old Blanket Order",
   "options": "Blanket Order"
  }
 ],
 "index_web_pages_for_search": 1,
 "istable": 1,
 "links": [],
 "modified": "2023-12-02 15:30:36.259449",
 "modified_by": "Administrator",
 "module": "Supplementary Invoice",
 "name": "Blanket Order Multi Select",
 "owner": "Administrator",
 "permissions": [],
 "sort_field": "modified",
 "sort_order": "DESC",
 "states": []
}